MitJisuanjijiaoyuZhongQueshiDeYikeFix1/README.md
MitJisuanjijiaoyuZhongQueshiDeYikeFix1/__init__.py
MitJisuanjijiaoyuZhongQueshiDeYikeFix1/__main__.py
MitJisuanjijiaoyuZhongQueshiDeYikeFix1/file.epub
MitJisuanjijiaoyuZhongQueshiDeYikeFix1/index.html
MitJisuanjijiaoyuZhongQueshiDeYikeFix1/css/__init__.py
MitJisuanjijiaoyuZhongQueshiDeYikeFix1/css/annotations.css
MitJisuanjijiaoyuZhongQueshiDeYikeFix1/css/main.css
MitJisuanjijiaoyuZhongQueshiDeYikeFix1/css/normalize.css
MitJisuanjijiaoyuZhongQueshiDeYikeFix1/css/popup.css
MitJisuanjijiaoyuZhongQueshiDeYikeFix1/font/__init__.py
MitJisuanjijiaoyuZhongQueshiDeYikeFix1/font/fontello.eot
MitJisuanjijiaoyuZhongQueshiDeYikeFix1/font/fontello.svg
MitJisuanjijiaoyuZhongQueshiDeYikeFix1/font/fontello.ttf
MitJisuanjijiaoyuZhongQueshiDeYikeFix1/font/fontello.woff
MitJisuanjijiaoyuZhongQueshiDeYikeFix1/img/__init__.py
MitJisuanjijiaoyuZhongQueshiDeYikeFix1/img/annotator-glyph-sprite.png
MitJisuanjijiaoyuZhongQueshiDeYikeFix1/img/annotator-icon-sprite.png
MitJisuanjijiaoyuZhongQueshiDeYikeFix1/img/apple-touch-icon.png
MitJisuanjijiaoyuZhongQueshiDeYikeFix1/img/cancelfullscreen.png
MitJisuanjijiaoyuZhongQueshiDeYikeFix1/img/close.png
MitJisuanjijiaoyuZhongQueshiDeYikeFix1/img/fullscreen.png
MitJisuanjijiaoyuZhongQueshiDeYikeFix1/img/loader.gif
MitJisuanjijiaoyuZhongQueshiDeYikeFix1/img/menu-icon.png
MitJisuanjijiaoyuZhongQueshiDeYikeFix1/img/save.png
MitJisuanjijiaoyuZhongQueshiDeYikeFix1/img/saved.png
MitJisuanjijiaoyuZhongQueshiDeYikeFix1/img/settings-s.png
MitJisuanjijiaoyuZhongQueshiDeYikeFix1/img/settings.png
MitJisuanjijiaoyuZhongQueshiDeYikeFix1/img/star.png
MitJisuanjijiaoyuZhongQueshiDeYikeFix1/js/__init__.py
MitJisuanjijiaoyuZhongQueshiDeYikeFix1/js/epub.js
MitJisuanjijiaoyuZhongQueshiDeYikeFix1/js/epub.min.js
MitJisuanjijiaoyuZhongQueshiDeYikeFix1/js/epub.min.map
MitJisuanjijiaoyuZhongQueshiDeYikeFix1/js/hooks.min.js
MitJisuanjijiaoyuZhongQueshiDeYikeFix1/js/hooks.min.map
mit_jisuanjijiaoyu_zhong_queshi_de_yike_fix1-2025.3.25.0.dist-info/METADATA
mit_jisuanjijiaoyu_zhong_queshi_de_yike_fix1-2025.3.25.0.dist-info/WHEEL
mit_jisuanjijiaoyu_zhong_queshi_de_yike_fix1-2025.3.25.0.dist-info/entry_points.txt
mit_jisuanjijiaoyu_zhong_queshi_de_yike_fix1-2025.3.25.0.dist-info/top_level.txt
mit_jisuanjijiaoyu_zhong_queshi_de_yike_fix1-2025.3.25.0.dist-info/RECORD
